oandadata/__init__.py
oandadata/retriever.py
oandadata-0.1.4.dist-info/License
oandadata-0.1.4.dist-info/METADATA
oandadata-0.1.4.dist-info/WHEEL
oandadata-0.1.4.dist-info/RECORD
